weaviate_classification/__init__.py
weaviate_classification/classify.py
weaviate_classification/confidence.py
weaviate_classification/data_configuration.py
weaviate_classification/debug.py
weaviate_classification/imports.py
weaviate_classification/parser.py
weaviate_classification/process_result.py
weaviate_classification/query.py
weaviate_classification/schema.py
weaviate_classification/utilities.py
weaviate_classification-0.1.14.dist-info/METADATA
weaviate_classification-0.1.14.dist-info/WHEEL
weaviate_classification-0.1.14.dist-info/top_level.txt
weaviate_classification-0.1.14.dist-info/RECORD
