Metadata-Version: 2.1
Name: weaviate-classification
Version: 0.1.14
Summary: A weaviate python data classification module.
Home-page: UNKNOWN
Author: SeMI Technologies
Author-email: hello@semi.technology
License: UNKNOWN
Platform: UNKNOWN
Requires-Python: >=3.6
Requires-Dist: weaviate-client (>=2.2.1)
Requires-Dist: PyYAML (==5.3.1)
Requires-Dist: openpyxl (==3.0.5)
